isevenoroddpkg/__init__.py
isevenoroddpkg/main.py
isevenoroddpkg-1.0.0.dist-info/LICENSE
isevenoroddpkg-1.0.0.dist-info/METADATA
isevenoroddpkg-1.0.0.dist-info/WHEEL
isevenoroddpkg-1.0.0.dist-info/top_level.txt
isevenoroddpkg-1.0.0.dist-info/RECORD
