Metadata-Version: 2.1
Name: isevenoroddpkg
Version: 1.0.0
Summary: Number validator
Home-page: UNKNOWN
Author: Parmeshwar
Author-email: parmeshwar@mindkosh.com
License: UNKNOWN
Keywords: even-odd-validator
Platform: UNKNOWN
Requires-Python: >=3.7
Requires-Dist: validators ==0.20.0
